{
  "multiprocessing": {
    "gb_per_process": 0.5,
    "num_processes": 0
  },
  "environment": {
    "working_directory": "~/Documents/ESA/data/sim",
    "debug": false,
    "verbose": false
  },
  "sixte": {
    "pn_instrument_dir": "/home/bojantodorkov/simput/share/sixte/instruments/xmm/epicpn",
    "mos_instrument_dir": "/home/bojantodorkov/simput/share/sixte/instruments/xmm/epicmos",
    "res_mult": [1, 2, 4],
    "exposure": [100000]
  },
  "simput": {
    "order": "normal"
  },
  "xmm": {
    "mode": {
      "img":  1,
      "agn":  0,
      "background":  0,
      "test_grid": 1
    },
    "sim_seperate_ccds": false,
    "fov": 0.8
  }
}